math_info_ifrn_2M.py
math_info_ifrn_2m-0.1.0.dist-info/METADATA
math_info_ifrn_2m-0.1.0.dist-info/WHEEL
math_info_ifrn_2m-0.1.0.dist-info/top_level.txt
math_info_ifrn_2m-0.1.0.dist-info/RECORD
