Metadata-Version: 2.4
Name: math_info_ifrn_2M
Version: 0.1.0
Summary: Funções matemáticas para o curso de informática do IFRN-paas-2M
Author: Arthur Marques
Author-email: arthur.marques@ifrn.edu.br
Keywords: budega dificil do inferno
Dynamic: author
Dynamic: author-email
Dynamic: keywords
Dynamic: summary
